gguf_comfy/__init__.py
gguf_comfy/__main__.py
gguf_comfy/downloader.py
gguf_comfy-0.2.1.dist-info/LICENSE
gguf_comfy-0.2.1.dist-info/WHEEL
gguf_comfy-0.2.1.dist-info/METADATA
gguf_comfy-0.2.1.dist-info/RECORD
