Metadata-Version: 2.1
Name: gguf-comfy
Version: 0.2.1
Summary: run flux1/sd3 model with beginner GPU (low cost) or even CPU
Author-email: calcuis <info@calcu.io>
Classifier: License :: OSI Approved :: MIT License
Requires-Dist: tqdm
Project-URL: Download, https://github.com/calcuis/gguf/releases
Project-URL: GitHub, https://github.com/calcuis/gguf-comfy
Project-URL: Homepage, https://gguf.org
Project-URL: reddit, https://www.reddit.com/r/gguf
